Metadata-Version: 2.1
Name: test-pkg-hamza
Version: 0.1.0
Summary: Database package for turnover crm
Home-page: https://github.com
Author: Hamza Farooq
Author-email: hamza.farooq@cloudconda.com
License: UNKNOWN
Platform: UNKNOWN
Classifier: Development Status :: 1 - Planning
Classifier: Intended Audience :: Developers
Classifier: License :: OSI Approved :: BSD License
Classifier: Operating System :: POSIX :: Linux
Classifier: Programming Language :: Python :: 3.8
Classifier: Programming Language :: Python :: 3.10
